README.rst
setup.py
feeder/__init__.py
feeder/cli.py
feeder/dictconfig.py
feeder/feeder.py
feeder/format_mappings.py
feeder/formatters.py
feeder/logger.py
feeder/six.py
feeder/transports.py
feeder.egg-info/PKG-INFO
feeder.egg-info/SOURCES.txt
feeder.egg-info/dependency_links.txt
feeder.egg-info/entry_points.txt
feeder.egg-info/requires.txt
feeder.egg-info/top_level.txt